R3/ext32.sv
module ext32 #(
    parameter OUT_WIDTH = 32
)(
    input logic     [1:0]               ImmSrc, //input that controls whether sign extension takes place.
    input logic     [31:7]              msb25,
    output logic    [OUT_WIDTH-1:0]     ImmExt
);

always_comb begin
    ImmExt[31:12] = {20{msb25[31]}};
    case(ImmSrc)
        /*I*/   2'b00:  ImmExt[11:0] = msb25[31:20];
        /*S*/   2'b01:  ImmExt[11:0] = {msb25[31:25], msb25[11:7]};
        /*B*/   2'b10:  ImmExt[11:0] = {msb25[7], msb25[30:25], msb25[11:8], 1'b0};
        /*U*/   2'b11:  ImmExt = {msb25[31:12], 12'b0};
                default: 
    endcase
end

endmodule

R3/MAINdec.sv
module MAINdec #(
    parameter   /*I-type Op*/   LOAD = 7'd3, I_AL = 7'd19, JALR = 7'd103,
                /*S-type Op*/   STORE = 7'd35,
                /*R-type Op*/   REG = 7'd51,
                /*B-type Op*/   BRANCH = 7'd99,
                /*U-type Op*/   AUIPC = 7'd23, LUI = 7'd55,
                /*J-type Op*/   JAL = 7'd111
)(
    input logic     [6:0]           Op,         //Instruction_word[6:0]
    output logic                    RegWrite,   //Write enable for the register file
    output logic                    ALUsrc,     //Inverted flag for R-type Op
    output logic    [1:0]           ALUOp,      //Control signal for ALUdec
    output logic    [1:0]           ImmSrc,     //Controls sign extension block
    output logic                    Branch      //Flag for B-type Op
);

//ALUOp logic: ALUOp determines how the ALUCtrl is decoded.
always_comb
    case(Op)
        //Load and Store employ the ALU add configuration
        LOAD: ALUOp = 2'b00;
        STORE: ALUOp = 2'b00;

        //Branch (beq) employs the ALU subtract configuration
        BRANCH: ALUOp = 2'b01;

        //Arithmetic & Logic (A&L) map funct3 to ALUCtrl, using funct7[5] to differentiate add from sub
        REG: ALUOp = 2'b10;
        I_AL: ALUOp = 2'b10; 

        default: ALUOp = 2'b00;
    endcase
    
/*RegWrite LOGIC:   only certain types of instructions write to regFiles, e.g. U-type do not.
                    The true cases are written but the false are given value 0 implicitly by default case*/
always_comb begin
    case (Op)
        //I-type
        LOAD: RegWrite = 1'b1; 
        I_AL: RegWrite = 1'b1;
        JALR: RegWrite = 1'b1;

        //R-type
        REG: RegWrite = 1'b1;

        //U-type
        AUIPC: RegWrite = 1'b1;
        LUI: RegWrite = 1'b1;

        //J-type
        JAL: RegWrite = 1'b1;

        default: RegWrite = 1'b0;
    endcase
end

//ALUsrc LOGIC: all instructions use a form of the immediate (1) apart from R type (0)
always_comb begin
    ALUsrc = ~(Op == REG);
end

/*ImmSrc LOGIC: The immediate operand is represented by different sections of the instruction word
                depending on the instruction type (I, U, S, B). R-type is don't care*/
always_comb begin
    case (Op)
        //I-type
        LOAD: ImmSrc = 2'b00;
        I_AL: ImmSrc = 2'b00;
        JALR: ImmSrc = 2'b00;

        //S-type
        STORE: ImmSrc = 2'b01;

        //B-type
        BRANCH: ImmSrc = 2'b10;

        //U-type
        AUIPC: ImmSrc = 2'b11;
        LUI:   ImmSrc = 2'b11;

        //R-type XX set to 00

        default: ImmSrc = 2'b00;
    endcase
end

//BRANCH Logic: identity whether instruction is B-type
always_comb
    Branch = (Op == BRANCH);

endmodule

R3/ControlUnit/ALUdec.sv
module ALUdec #(
    input logic     [1:0]       ALUop,
    input logic     [2:0]       funct3,
    input logic                 funct7_5,
    output logic    [2:0]       ALUctrl
);

/*ALUCtrl LOGIC:    this 3-bit control input has been decoded by mapping each bit from funct3 to ALUctrl with
                    a boolean expression.*/
always_comb begin
    case (ALUOp)
        //LOAD & STORE
        2'b00: ALUctrl = 3'b000

        //BRANCH
        2'b01: ALUctrl = 3'b001

        //ARITHMETIC & LOGIC (R or I)
        2'b10:  begin
                ALUctrl[2] = ~(funct3[2]) & funct3[1];
                ALUctrl[1] = funct3[2] & funct3[1];
                ALUctrl[0] = ~(funct3[2])&funct3[1] | funct3[1] & funct3[0] | ~(funct3) & funct7_5;
                end

        default: ALUctrl = 3'b0;
    endcase
end

endmodule

R3/cu.sv
module cu (
    input logic                     EQ,         //high for OpA == OpB
    input logic     [6:0]           Op,         //Ins[6:0]
    input logic     [2:0]           funct3,     //Ins[14:12]
    input logic                     funct7_5,   //Ins[30]
    output logic                    RegWrite,   //Write enable for the register file
    output logic    [2:0]           ALUctrl,    //Configures ALU for required operation
    output logic                    ALUsrc,     //Selects register or immediate operand 
    output logic    [1:0]           ImmSrc,     //Controls sign extension block
    output logic                    PCsrc       //Selects PC addressing between PC:=PC+4 and PC:=Imm32
);

wire   [1:0]          ALUOp;
logic                 Branch;
logic                 NEG;

assign NEG = funct3[0];

ALUdec ALUdec (
    .ALUOp(ALUOp),
    .funct3(funct3),
    .funct7_5(funct7_5),
    .ALUctrl(ALUctrl)
);

MAINdec MAINdec (
    .Op(Op),
    .RegWrite(RegWrite),
    .ALUsrc(ALUsrc),
    .ALUOp(ALUOp),
    .ImmSrc(ImmSrc),
    .Branch(Branch)  
);

//PCsrc logic
always_comb
    PCsrc = (NEG ^ EQ) & Branch;
endmodule

R3/rom.sv
module rom #(
    parameter   ADDRESS_WIDTH = 20,
                DATA_WIDTH = 8    
)(
    input logic [ADDRESS_WIDTH-1:0] A,
    output logic [31:0] RD
);

logic [DATA_WIDTH-1:0] rom_array [2**ADDRESS_WIDTH-1:0];

initial begin
    $display("Loading rom.");
    $readmemh("program.mem", rom_array);
end

always_comb begin
    // output is asynchronous
    RD = {rom_array[A], rom_array[A+1], rom_array[A+2], rom_array[A+3]};
end

endmodule

R3/control.sv
module control (
    input logic                     clk,
    input logic     [31:0]          PC,
    input logic                     EQ,
    output logic                    RegWrite,   //Write enable for the register file
    output logic    [2:0]           ALUctrl,    //Configures ALU for required operation
    output logic                    ALUsrc,     //Selects register or immediate operand 
    output logic    [1:0]           ImmSrc,     //Controls sign extension block
    output logic                    PCsrc,       //Selects PC addressing between PC:=PC+4 and PC:=Imm32
    output logic    [31:0]          ImmExt
);

logic [31:0] ins;
logic [31:0] PC1;

rom rom (
    .A(PC1),
    .RD(ins)
);

cu cu (
    .EQ(EQ),
    .Op(ins[6:0]),
    .funct3(ins[14:12]),
    .funct7_5(ins[30]),
    .RegWrite(RegWrite),
    .ALUctrl(ALUctrl),
    .ALUsrc(ALUsrc),
    .ImmSrc(ImmSrc),
    .PCsrc(PCsrc)
);

ext32 ext32 (
    .ImmSrc(ImmSrc),
    .msb25(ins[31:7]),
    .ImmExt(ImmExt)
);

always_ff @(posedge clk)
    PC1 <= PC;

endmodule

R3/Vcontrol.vcd
$version Generated by VerilatedVcd $end
$date Thu Nov 24 15:28:17 2022 $end
$timescale 1ps $end

 $scope module TOP $end
  $var wire  3 1 ALUctrl [2:0] $end
  $var wire  1 2 ALUsrc $end
  $var wire  1 / EQ $end
  $var wire 32 5 ImmExt [31:0] $end
  $var wire  2 3 ImmSrc [1:0] $end
  $var wire 32 . PC [31:0] $end
  $var wire  1 4 PCsrc $end
  $var wire  1 0 RegWrite $end
  $var wire  1 - clk $end
  $scope module control $end
   $var wire  3 1 ALUctrl [2:0] $end
   $var wire  1 2 ALUsrc $end
   $var wire  1 / EQ $end
   $var wire 32 5 ImmExt [31:0] $end
   $var wire  2 3 ImmSrc [1:0] $end
   $var wire 32 . PC [31:0] $end
   $var wire 32 $ PC1 [31:0] $end
   $var wire  1 4 PCsrc $end
   $var wire  1 0 RegWrite $end
   $var wire  1 - clk $end
   $var wire 32 # ins [31:0] $end
   $scope module cu $end
    $var wire  2 ( ALUOp [1:0] $end
    $var wire  3 1 ALUctrl [2:0] $end
    $var wire  1 2 ALUsrc $end
    $var wire  1 ) Branch $end
    $var wire  1 / EQ $end
    $var wire  2 3 ImmSrc [1:0] $end
    $var wire  1 * NEG $end
    $var wire  7 % Op [6:0] $end
    $var wire  1 4 PCsrc $end
    $var wire  1 0 RegWrite $end
    $var wire  3 & funct3 [2:0] $end
    $var wire  1 ' funct7_5 $end
    $scope module ALUdec $end
     $var wire  2 ( ALUOp [1:0] $end
     $var wire  3 1 ALUctrl [2:0] $end
     $var wire  3 & funct3 [2:0] $end
     $var wire  1 ' funct7_5 $end
    $upscope $end
    $scope module MAINdec $end
     $var wire  2 ( ALUOp [1:0] $end
     $var wire  1 2 ALUsrc $end
     $var wire  7 < AUIPC [6:0] $end
     $var wire  7 ; BRANCH [6:0] $end
     $var wire  1 ) Branch $end
     $var wire  7 7 I_AL [6:0] $end
     $var wire  2 3 ImmSrc [1:0] $end
     $var wire  7 > JAL [6:0] $end
     $var wire  7 8 JALR [6:0] $end
     $var wire  7 6 LOAD [6:0] $end
     $var wire  7 = LUI [6:0] $end
     $var wire  7 % Op [6:0] $end
     $var wire  7 : REG [6:0] $end
     $var wire  1 0 RegWrite $end
     $var wire  7 9 STORE [6:0] $end
    $upscope $end
   $upscope $end
   $scope module ext32 $end
    $var wire 32 5 ImmExt [31:0] $end
    $var wire  2 3 ImmSrc [1:0] $end
    $var wire 32 ? OUT_WIDTH [31:0] $end
    $var wire 25 + msb25 [31:7] $end
   $upscope $end
   $scope module rom $end
    $var wire 20 , A [19:0] $end
    $var wire 32 @ ADDRESS_WIDTH [31:0] $end
    $var wire 32 A DATA_WIDTH [31:0] $end
    $var wire 32 # RD [31:0] $end
   $upscope $end
  $upscope $end
 $upscope $end
$enddefinitions $end


#0
b00000000000000000000000000000000 #
b00000000000000000000000000000000 $
b0000000 %
b000 &
0'
b00 (
0)
0*
b0000000000000000000000000 +
b00000000000000000000 ,
0-
b00000000000000000000000000000000 .
1/
00
b000 1
02
b00 3
04
b00000000000000000000000000000000 5
b0000011 6
b0010011 7
b1100111 8
b0100011 9
b0110011 :
b1100011 ;
b0010111 <
b0110111 =
b1101111 >
b00000000000000000000000000100000 ?
b00000000000000000000000000010100 @
b00000000000000000000000000001000 A
#1
1-
12
#2
0-
#3
1-
#4
0-
#5
1-
#6
0-
#7
1-
#8
0-
#9
1-
#10
0-
#11
1-
#12
0-
b00000000000000000000000000000100 .
#13
b00001111111100000000001100010011 #
b00000000000000000000000000000100 $
b0010011 %
b10 (
b0000111111110000000000110 +
b00000000000000000100 ,
1-
10
b00000000000000000000000011111111 5
#14
0-
b00000000000000000000000000001000 .
#15
b00000000000000000000010100010011 #
b00000000000000000000000000001000 $
b0000000000000000000001010 +
b00000000000000001000 ,
1-
b00000000000000000000000000000000 5
#16
0-
b00000000000000000000000000001100 .
#17
b00000000000000000000010110010011 #
b00000000000000000000000000001100 $
b0000000000000000000001011 +
b00000000000000001100 ,
1-
#18
0-
b00000000000000000000000000010000 .
#19
b00000000000001011000010100010011 #
b00000000000000000000000000010000 $
b0000000000000101100001010 +
b00000000000000010000 ,
1-
#20
0-
b00000000000000000000000000010100 .
#21
b00000000000101011000010110010011 #
b00000000000000000000000000010100 $
b0000000000010101100001011 +
b00000000000000010100 ,
1-
b00000000000000000000000000000001 5
#22
0-
b00000000000000000000000000011000 .
#23
b11111110011001011001100011100011 #
b00000000000000000000000000011000 $
b1100011 %
b001 &
1'
b01 (
1)
1*
b1111111001100101100110001 +
b00000000000000011000 ,
1-
00
b001 1
b10 3
b11111111111111111111111111110000 5
#24
0-
b00000000000000000000000000011100 .
#25
b11111110000000110001000011100011 #
b00000000000000000000000000011100 $
b1111111000000011000100001 +
b00000000000000011100 ,
1-
b11111111111111111111111111100000 5
#26
0-
b00000000000000000000000000100000 .
#27
b11111110010000100000101011100011 #
b00000000000000000000000000100000 $
b000 &
0*
b1111111001000010000010101 +
b00000000000000100000 ,
1-
14
b11111111111111111111111111110100 5
#28
0-
b00000000000000000000000000100100 .
#29
b00000000000000000000000000000000 #
b00000000000000000000000000100100 $
b0000000 %
0'
b00 (
0)
b0000000000000000000000000 +
b00000000000000100100 ,
1-
b000 1
b00 3
04
b00000000000000000000000000000000 5
#30
0-
b00000000000000000000000000101000 .
#31
b00000000000000000000000000101000 $
b00000000000000101000 ,
1-
