R1/program_counter.sv
// module program_counter (
//     input  logic        clk,
//     input  logic        rst,
//     input  logic        PCsrc,
//     input  logic [31:0] ImmOp,
//     output logic [31:0] PC
// );
//     logic [31:0] branch_PC;
//     logic [31:0] inc_PC;
//     logic [31:0] next_PC;

//     adder branch_adder(
//         .op1(PC),
//         .op2(ImmOp),
//         .out(branch_PC)
//     );

//     adder inc_adder(
//         .op1(PC),
//         .op2(32'd4),
//         .out(inc_PC)
//     );

//     mux branch_sel(
//         .in1(branch_PC),
//         .in2(inc_PC),
//         .sel(PCsrc),
//         .out(next_PC)
//     );

//     register PCReg(
//         .clk(clk),
//         .rst(rst),
//         .in(next_PC),
//         .out(PC)
//     );

// endmodule

module program_counter (
    input  logic        clk,
    input  logic        rst,
    input  logic        PCsrc,
    input  logic [31:0] ImmOp,
    output logic [31:0] PC
);
    logic [31:0] branch_PC;
    logic [31:0] inc_PC;
    logic [31:0] next_PC;

    assign branch_PC = PC + ImmOp;
    assign inc_PC = PC + 32'd4;
    assign next_PC = PCsrc ? branch_PC : inc_PC;

    always_ff @(posedge clk) begin
        if (rst) PC <= 32'd0;
        else PC <= next_PC;
    end

endmodule

lab4_final/R1/program_counter.vcd
$version Generated by VerilatedVcd $end
$date Fri Nov 25 11:45:17 2022 $end
$timescale 1ps $end

 $scope module TOP $end
  $var wire 32 & ImmOp [31:0] $end
  $var wire 32 ' PC [31:0] $end
  $var wire  1 % PCsrc $end
  $var wire  1 # clk $end
  $var wire  1 $ rst $end
  $scope module program_counter $end
   $var wire 32 & ImmOp [31:0] $end
   $var wire 32 ' PC [31:0] $end
   $var wire  1 % PCsrc $end
   $var wire 32 ( branch_PC [31:0] $end
   $var wire  1 # clk $end
   $var wire 32 ) inc_PC [31:0] $end
   $var wire 32 * next_PC [31:0] $end
   $var wire  1 $ rst $end
  $upscope $end
 $upscope $end
$enddefinitions $end


#0
1#
1$
0%
b00000000000000000000000000000000 &
b00000000000000000000000000000000 '
b00000000000000000000000000000000 (
b00000000000000000000000000000100 )
b00000000000000000000000000000100 *
#1
0#
#2
1#
#3
0#
#4
1#
#5
0#
#6
1#
0$
b01100111000010000111000001100111 &
b01100111000010000111000001100111 (
#7
0#
#8
1#
b01000110111001111100110111000110 &
b00000000000000000000000000000100 '
b01000110111001111100110111001010 (
b00000000000000000000000000001000 )
b00000000000000000000000000001000 *
#9
0#
#10
1#
b01110010101101011001100100001000 &
b00000000000000000000000000001000 '
b01110010101101011001100100010000 (
b00000000000000000000000000001100 )
b00000000000000000000000000001100 *
#11
0#
#12
1#
b01010010100001011101100010111100 &
b00000000000000000000000000001100 '
b01010010100001011101100011001000 (
b00000000000000000000000000010000 )
b00000000000000000000000000010000 *
#13
0#
#14
1#
b01000011101110010111000011100100 &
b00000000000000000000000000010000 '
b01000011101110010111000011110100 (
b00000000000000000000000000010100 )
b00000000000000000000000000010100 *
#15
0#
#16
1#
b01100111001100100000100101011011 &
b00000000000000000000000000010100 '
b01100111001100100000100101101111 (
b00000000000000000000000000011000 )
b00000000000000000000000000011000 *
#17
0#
#18
1#
b00001111111000000101100000011011 &
b00000000000000000000000000011000 '
b00001111111000000101100000110011 (
b00000000000000000000000000011100 )
b00000000000000000000000000011100 *
#19
0#
#20
1#
b00111010101101010010001000000111 &
b00000000000000000000000000011100 '
b00111010101101010010001000100011 (
b00000000000000000000000000100000 )
b00000000000000000000000000100000 *
#21
0#
#22
1#
b01110100010011000111010000010010 &
b00000000000000000000000000100000 '
b01110100010011000111010000110010 (
b00000000000000000000000000100100 )
b00000000000000000000000000100100 *
#23
0#
#24
1#
b01011010001000000010111000010110 &
b00000000000000000000000000100100 '
b01011010001000000010111000111010 (
b00000000000000000000000000101000 )
b00000000000000000000000000101000 *
#25
0#
#26
1#
b01101110000100000001001101011100 &
b00000000000000000000000000101000 '
b01101110000100000001001110000100 (
b00000000000000000000000000101100 )
b00000000000000000000000000101100 *
#27
0#
#28
1#
b01110110100010011001000010001110 &
b00000000000000000000000000101100 '
b01110110100010011001000010111010 (
b00000000000000000000000000110000 )
b00000000000000000000000000110000 *
#29
0#
#30
1#
b00100001000011110100011000010010 &
b00000000000000000000000000110000 '
b00100001000011110100011001000010 (
b00000000000000000000000000110100 )
b00000000000000000000000000110100 *
#31
0#
#32
1#
b00010001010000111111101100010101 &
b00000000000000000000000000110100 '
b00010001010000111111101101001001 (
b00000000000000000000000000111000 )
b00000000000000000000000000111000 *
#33
0#
#34
1#
b01100101000111011011110110010101 &
b00000000000000000000000000111000 '
b01100101000111011011110111001101 (
b00000000000000000000000000111100 )
b00000000000000000000000000111100 *
#35
0#
#36
1#
b00010010101110010110010011001010 &
b00000000000000000000000000111100 '
b00010010101110010110010100000110 (
b00000000000000000000000001000000 )
b00000000000000000000000001000000 *
#37
0#
#38
1#
b00110110011101010011100010111110 &
b00000000000000000000000001000000 '
b00110110011101010011100011111110 (
b00000000000000000000000001000100 )
b00000000000000000000000001000100 *
#39
0#
#40
1#
b00101001110101010101001111111000 &
b00000000000000000000000001000100 '
b00101001110101010101010000111100 (
b00000000000000000000000001001000 )
b00000000000000000000000001001000 *
#41
0#
#42
1#
b01001110100101101110001001111100 &
b00000000000000000000000001001000 '
b01001110100101101110001011000100 (
b00000000000000000000000001001100 )
b00000000000000000000000001001100 *
#43
0#
#44
1#
b00111001010111001111001110010001 &
b00000000000000000000000001001100 '
b00111001010111001111001111011101 (
b00000000000000000000000001010000 )
b00000000000000000000000001010000 *
#45
0#
#46
1#
b01011100011111111011100010100010 &
b00000000000000000000000001010000 '
b01011100011111111011100011110010 (
b00000000000000000000000001010100 )
b00000000000000000000000001010100 *
#47
0#
#48
1#
b00001000110010100000111111100010 &
b00000000000000000000000001010100 '
b00001000110010100001000000110110 (
b00000000000000000000000001011000 )
b00000000000000000000000001011000 *
#49
0#
#50
1#
b01111111011110001011011011001100 &
b00000000000000000000000001011000 '
b01111111011110001011011100100100 (
b00000000000000000000000001011100 )
b00000000000000000000000001011100 *
#51
0#
#52
1#
b00111011000110111001101100100001 &
b00000000000000000000000001011100 '
b00111011000110111001101101111101 (
b00000000000000000000000001100000 )
b00000000000000000000000001100000 *
#53
0#
#54
1#
b00011101110001101011001101111010 &
b00000000000000000000000001100000 '
b00011101110001101011001111011010 (
b00000000000000000000000001100100 )
b00000000000000000000000001100100 *
#55
0#
#56
1#
b00100101011000101010010111111110 &
b00000000000000000000000001100100 '
b00100101011000101010011001100010 (
b00000000000000000000000001101000 )
b00000000000000000000000001101000 *
#57
0#
#58
1#
b00001110110010110100100001111101 &
b00000000000000000000000001101000 '
b00001110110010110100100011100101 (
b00000000000000000000000001101100 )
b00000000000000000000000001101100 *
#59
0#
#60
1#
b00000111000010000101010101011011 &
b00000000000000000000000001101100 '
b00000111000010000101010111000111 (
b00000000000000000000000001110000 )
b00000000000000000000000001110000 *
#61
0#
#62
1#
b00011011111000000011001100010100 &
b00000000000000000000000001110000 '
b00011011111000000011001110000100 (
b00000000000000000000000001110100 )
b00000000000000000000000001110100 *
#63
0#
#64
1#
b01001101100010000001101001000101 &
b00000000000000000000000001110100 '
b01001101100010000001101010111001 (
b00000000000000000000000001111000 )
b00000000000000000000000001111000 *
#65
0#
#66
1#
b01010101110100111010101000011110 &
b00000000000000000000000001111000 '
b01010101110100111010101010010110 (
b00000000000000000000000001111100 )
b00000000000000000000000001111100 *
#67
0#
#68
1#
b00000010111010001010001101111100 &
b00000000000000000000000001111100 '
b00000010111010001010001111111000 (
b00000000000000000000000010000000 )
b00000000000000000000000010000000 *
#69
0#
#70
1#
b00010100011011111110100000001011 &
b00000000000000000000000010000000 '
b00010100011011111110100010001011 (
b00000000000000000000000010000100 )
b00000000000000000000000010000100 *
#71
0#
#72
1#
b01001000100010010100001100100110 &
b00000000000000000000000010000100 '
b01001000100010010100001110101010 (
b00000000000000000000000010001000 )
b00000000000000000000000010001000 *
#73
0#
#74
1#
b01010101011011100111110000111000 &
b00000000000000000000000010001000 '
b01010101011011100111110011000000 (
b00000000000000000000000010001100 )
b00000000000000000000000010001100 *
#75
0#
#76
1#
b01011000001010010101100011110000 &
b00000000000000000000000010001100 '
b01011000001010010101100101111100 (
b00000000000000000000000010010000 )
b00000000000000000000000010010000 *
#77
0#
#78
1#
b00101111101110110100110010000010 &
b00000000000000000000000010010000 '
b00101111101110110100110100010010 (
b00000000000000000000000010010100 )
b00000000000000000000000010010100 *
#79
0#
#80
1#
b01100101010011101101010001010011 &
b00000000000000000000000010010100 '
b01100101010011101101010011100111 (
b00000000000000000000000010011000 )
b00000000000000000000000010011000 *
#81
0#
#82
1#
b00010010110111100111101011110111 &
b00000000000000000000000010011000 '
b00010010110111100111101110001111 (
b00000000000000000000000010011100 )
b00000000000000000000000010011100 *
#83
0#
#84
1#
b00100100000001111100000010010100 &
b00000000000000000000000010011100 '
b00100100000001111100000100110000 (
b00000000000000000000000010100000 )
b00000000000000000000000010100000 *
#85
0#
#86
1#
b00111111011011110000001001101001 &
b00000000000000000000000010100000 '
b00111111011011110000001100001001 (
b00000000000000000000000010100100 )
b00000000000000000000000010100100 *
#87
0#
#88
1#
b00000000111011101000111001010011 &
b00000000000000000000000010100100 '
b00000000111011101000111011110111 (
b00000000000000000000000010101000 )
b00000000000000000000000010101000 *
#89
0#
#90
1#
b00011010100100010101000100100010 &
b00000000000000000000000010101000 '
b00011010100100010101000111001010 (
b00000000000000000000000010101100 )
b00000000000000000000000010101100 *
#91
0#
#92
1#
b01100000011111100100100001111011 &
b00000000000000000000000010101100 '
b01100000011111100100100100100111 (
b00000000000000000000000010110000 )
b00000000000000000000000010110000 *
#93
0#
#94
1#
b00010010001100101000100101101000 &
b00000000000000000000000010110000 '
b00010010001100101000101000011000 (
b00000000000000000000000010110100 )
b00000000000000000000000010110100 *
#95
0#
#96
1#
b01111111101011110000111010110111 &
b00000000000000000000000010110100 '
b01111111101011110000111101101011 (
b00000000000000000000000010111000 )
b00000000000000000000000010111000 *
#97
0#
#98
1#
b01110011001101111010110101000101 &
b00000000000000000000000010111000 '
b01110011001101111010110111111101 (
b00000000000000000000000010111100 )
b00000000000000000000000010111100 *
#99
0#
#100
1#
b01001000101001111100001000100110 &
b00000000000000000000000010111100 '
b01001000101001111100001011100010 (
b00000000000000000000000011000000 )
b00000000000000000000000011000000 *
#101
0#
#102
1#
b00000000000000000000000011000000 '
b01001000101001111100001011100110 (
b00000000000000000000000011000100 )
b00000000000000000000000011000100 *
#103
0#
#104
1#
b00000000000000000000000011000100 '
b01001000101001111100001011101010 (
b00000000000000000000000011001000 )
b00000000000000000000000011001000 *
#105
0#
#106
1#
b00000000000000000000000011001000 '
b01001000101001111100001011101110 (
b00000000000000000000000011001100 )
b00000000000000000000000011001100 *
#107
0#
#108
1#
b00000000000000000000000011001100 '
b01001000101001111100001011110010 (
b00000000000000000000000011010000 )
b00000000000000000000000011010000 *
#109
0#
#110
1#
b00000000000000000000000011010000 '
b01001000101001111100001011110110 (
b00000000000000000000000011010100 )
b00000000000000000000000011010100 *
#111
0#
#112
1#
b00000000000000000000000011010100 '
b01001000101001111100001011111010 (
b00000000000000000000000011011000 )
b00000000000000000000000011011000 *
#113
0#
#114
1#
b00000000000000000000000011011000 '
b01001000101001111100001011111110 (
b00000000000000000000000011011100 )
b00000000000000000000000011011100 *
#115
0#
#116
1#
b00000000000000000000000011011100 '
b01001000101001111100001100000010 (
b00000000000000000000000011100000 )
b00000000000000000000000011100000 *
#117
0#
#118
1#
b00000000000000000000000011100000 '
b01001000101001111100001100000110 (
b00000000000000000000000011100100 )
b00000000000000000000000011100100 *
#119
0#
#120
1#
b00000000000000000000000011100100 '
b01001000101001111100001100001010 (
b00000000000000000000000011101000 )
b00000000000000000000000011101000 *
#121
0#
#122
1#
b00000000000000000000000011101000 '
b01001000101001111100001100001110 (
b00000000000000000000000011101100 )
b00000000000000000000000011101100 *
#123
0#
#124
1#
b00000000000000000000000011101100 '
b01001000101001111100001100010010 (
b00000000000000000000000011110000 )
b00000000000000000000000011110000 *
#125
0#
#126
1#
b00000000000000000000000011110000 '
b01001000101001111100001100010110 (
b00000000000000000000000011110100 )
b00000000000000000000000011110100 *
#127
0#
#128
1#
b00000000000000000000000011110100 '
b01001000101001111100001100011010 (
b00000000000000000000000011111000 )
b00000000000000000000000011111000 *
#129
0#
#130
1#
b00000000000000000000000011111000 '
b01001000101001111100001100011110 (
b00000000000000000000000011111100 )
b00000000000000000000000011111100 *
#131
0#
#132
1#
b00000000000000000000000011111100 '
b01001000101001111100001100100010 (
b00000000000000000000000100000000 )
b00000000000000000000000100000000 *
#133
0#
#134
1#
b00000000000000000000000100000000 '
b01001000101001111100001100100110 (
b00000000000000000000000100000100 )
b00000000000000000000000100000100 *
#135
0#
#136
1#
b00000000000000000000000100000100 '
b01001000101001111100001100101010 (
b00000000000000000000000100001000 )
b00000000000000000000000100001000 *
#137
0#
#138
1#
b00000000000000000000000100001000 '
b01001000101001111100001100101110 (
b00000000000000000000000100001100 )
b00000000000000000000000100001100 *
#139
0#
#140
1#
b00000000000000000000000100001100 '
b01001000101001111100001100110010 (
b00000000000000000000000100010000 )
b00000000000000000000000100010000 *
#141
0#
#142
1#
b00000000000000000000000100010000 '
b01001000101001111100001100110110 (
b00000000000000000000000100010100 )
b00000000000000000000000100010100 *
#143
0#
#144
1#
b00000000000000000000000100010100 '
b01001000101001111100001100111010 (
b00000000000000000000000100011000 )
b00000000000000000000000100011000 *
#145
0#
#146
1#
b00000000000000000000000100011000 '
b01001000101001111100001100111110 (
b00000000000000000000000100011100 )
b00000000000000000000000100011100 *
#147
0#
#148
1#
b00000000000000000000000100011100 '
b01001000101001111100001101000010 (
b00000000000000000000000100100000 )
b00000000000000000000000100100000 *
#149
0#
#150
1#
b00000000000000000000000100100000 '
b01001000101001111100001101000110 (
b00000000000000000000000100100100 )
b00000000000000000000000100100100 *
#151
0#
#152
1#
b00000000000000000000000100100100 '
b01001000101001111100001101001010 (
b00000000000000000000000100101000 )
b00000000000000000000000100101000 *
#153
0#
#154
1#
b00000000000000000000000100101000 '
b01001000101001111100001101001110 (
b00000000000000000000000100101100 )
b00000000000000000000000100101100 *
#155
0#
#156
1#
b00000000000000000000000100101100 '
b01001000101001111100001101010010 (
b00000000000000000000000100110000 )
b00000000000000000000000100110000 *
#157
0#
#158
1#
b00000000000000000000000100110000 '
b01001000101001111100001101010110 (
b00000000000000000000000100110100 )
b00000000000000000000000100110100 *
#159
0#
#160
1#
b00000000000000000000000100110100 '
b01001000101001111100001101011010 (
b00000000000000000000000100111000 )
b00000000000000000000000100111000 *
#161
0#
#162
1#
b00000000000000000000000100111000 '
b01001000101001111100001101011110 (
b00000000000000000000000100111100 )
b00000000000000000000000100111100 *
#163
0#
#164
1#
b00000000000000000000000100111100 '
b01001000101001111100001101100010 (
b00000000000000000000000101000000 )
b00000000000000000000000101000000 *
#165
0#
#166
1#
b00000000000000000000000101000000 '
b01001000101001111100001101100110 (
b00000000000000000000000101000100 )
b00000000000000000000000101000100 *
#167
0#
#168
1#
b00000000000000000000000101000100 '
b01001000101001111100001101101010 (
b00000000000000000000000101001000 )
b00000000000000000000000101001000 *
#169
0#
#170
1#
b00000000000000000000000101001000 '
b01001000101001111100001101101110 (
b00000000000000000000000101001100 )
b00000000000000000000000101001100 *
#171
0#
#172
1#
b00000000000000000000000101001100 '
b01001000101001111100001101110010 (
b00000000000000000000000101010000 )
b00000000000000000000000101010000 *
#173
0#
#174
1#
b00000000000000000000000101010000 '
b01001000101001111100001101110110 (
b00000000000000000000000101010100 )
b00000000000000000000000101010100 *
#175
0#
#176
1#
b00000000000000000000000101010100 '
b01001000101001111100001101111010 (
b00000000000000000000000101011000 )
b00000000000000000000000101011000 *
#177
0#
#178
1#
b00000000000000000000000101011000 '
b01001000101001111100001101111110 (
b00000000000000000000000101011100 )
b00000000000000000000000101011100 *
#179
0#
#180
1#
b00000000000000000000000101011100 '
b01001000101001111100001110000010 (
b00000000000000000000000101100000 )
b00000000000000000000000101100000 *
#181
0#
#182
1#
b00000000000000000000000101100000 '
b01001000101001111100001110000110 (
b00000000000000000000000101100100 )
b00000000000000000000000101100100 *
#183
0#
#184
1#
b00000000000000000000000101100100 '
b01001000101001111100001110001010 (
b00000000000000000000000101101000 )
b00000000000000000000000101101000 *
#185
0#
#186
1#
b00000000000000000000000101101000 '
b01001000101001111100001110001110 (
b00000000000000000000000101101100 )
b00000000000000000000000101101100 *
#187
0#
#188
1#
b00000000000000000000000101101100 '
b01001000101001111100001110010010 (
b00000000000000000000000101110000 )
b00000000000000000000000101110000 *
#189
0#
#190
1#
b00000000000000000000000101110000 '
b01001000101001111100001110010110 (
b00000000000000000000000101110100 )
b00000000000000000000000101110100 *
#191
0#
#192
1#
b00000000000000000000000101110100 '
b01001000101001111100001110011010 (
b00000000000000000000000101111000 )
b00000000000000000000000101111000 *
#193
0#
#194
1#
b00000000000000000000000101111000 '
b01001000101001111100001110011110 (
b00000000000000000000000101111100 )
b00000000000000000000000101111100 *
#195
0#
#196
1#
b00000000000000000000000101111100 '
b01001000101001111100001110100010 (
b00000000000000000000000110000000 )
b00000000000000000000000110000000 *
#197
0#
#198
1#
b00000000000000000000000110000000 '
b01001000101001111100001110100110 (
b00000000000000000000000110000100 )
b00000000000000000000000110000100 *
