lab4_final/R2/alu.sv
module alu (
    input logic [31:0] aluOp1,
    input logic [31:0] aluOp2,
    input logic [2:0] aluCTR,
    output logic [31:0] sum,
    output logic eq
);

always_comb begin
    if(aluCTR == 3'b0) sum = aluOp1 + aluOp2;
    else sum = 32'b0;
    if(aluOp1 == aluOp2) eq = 1;
    else eq = 0;
end

endmodule

R2/mux.sv
module mux(
    input logic [31:0] regOp2,
    input logic [31:0] immOp,
    input logic aluSrc,
    output logic [31:0] aluOp2
);

    always_comb
        aluOp2 = aluSrc ? immOp : regOp2;
        

endmodule

R2/regFile.sv
module regFile #(
    parameter ADDRESS_WIDTH = 5,
              DATA_WIDTH = 32
)(
    input logic clk,
    input logic [ADDRESS_WIDTH-1:0] ad1,
    input logic [ADDRESS_WIDTH-1:0] ad2,
    input logic [ADDRESS_WIDTH-1:0] ad3,
    input logic we3,
    input logic [DATA_WIDTH-1:0] wd3,
    output logic [DATA_WIDTH-1:0] rd1,
    output logic [DATA_WIDTH-1:0] rd2,
    output logic [DATA_WIDTH-1:0] a0
);

logic [DATA_WIDTH-1:0] rom_array [2**ADDRESS_WIDTH-1:0];


/* initial begin
    $readmemh("sinerom.mem", rom_array);
end; */

always_comb begin
    rd1 = rom_array[ad1];
    rd2 = rom_array[ad2];
    a0 = rom_array[5'b1010];
end;

always_ff @(posedge clk)
    if(we3) rom_array[ad3] <= wd3;

    
endmodule

lab4_final/R2/red.sv
module red #(
    parameter ADDRESS_WIDTH = 5,
              DATA_WIDTH = 32
)(
    input wire clk,
    output wire [31:0] a0,
    input wire [ADDRESS_WIDTH - 1:0] ad1,
    input wire [ADDRESS_WIDTH - 1:0] ad2,
    input wire [ADDRESS_WIDTH - 1:0] ad3,
    input wire we3,
    input wire aluSrc,
    input wire [2:0] aluCTR,
    output wire eq,
    input wire [DATA_WIDTH - 1:0] immOp
);

wire [DATA_WIDTH - 1:0] aluOut;
wire [DATA_WIDTH - 1:0] aluOp1;
wire [DATA_WIDTH - 1:0] regOp2;
wire [DATA_WIDTH - 1:0] aluOp2;


regFile myRegFile(
    .ad1(ad1),
    .ad2(ad2),
    .ad3(ad3),
    .we3(we3),
    .wd3(aluOut),
    .rd1(aluOp1),
    .rd2(regOp2),
    .a0(a0),
    .clk(clk)
);

mux myMux(
    .regOp2(regOp2),
    .aluSrc(aluSrc),
    .immOp(immOp),
    .aluOp2(aluOp2)
);

alu myAlu(
    .aluOp1(aluOp1),
    .aluOp2(aluOp2),
    .aluCTR(aluCTR),
    .sum(aluOut),
    .eq(eq)
);

endmodule

R3/ext32.sv
module ext32 #(
    parameter OUT_WIDTH = 32
)(
    input logic     [1:0]               ImmSrc, //input that controls whether sign extension takes place.
    input logic     [31:7]              msb25,
    output logic    [OUT_WIDTH-1:0]     ImmExt
);

always_comb begin
    ImmExt[31:12] = {20{msb25[31]}};
    case(ImmSrc)
        /*I*/   2'b00:  ImmExt[11:0] = msb25[31:20];
        /*S*/   2'b01:  ImmExt[11:0] = {msb25[31:25], msb25[11:7]};
        /*B*/   2'b10:  ImmExt[11:0] = {msb25[7], msb25[30:25], msb25[11:8], 1'b0};
        /*U*/   2'b11:  ImmExt = {msb25[31:12], 12'b0};
                default: 
    endcase
end

endmodule

lab4_final/R3/MAINdec.sv
module MAINdec #(
    parameter   /*I-type Op*/   LOAD = 7'd3, I_AL = 7'd19, JALR = 7'd103,
                /*S-type Op*/   STORE = 7'd35,
                /*R-type Op*/   REG = 7'd51,
                /*B-type Op*/   BRANCH = 7'd99,
                /*U-type Op*/   AUIPC = 7'd23, LUI = 7'd55,
                /*J-type Op*/   JAL = 7'd111
)(
    input logic     [6:0]           Op,         //Instruction_word[6:0]
    output logic                    RegWrite,   //Write enable for the register file
    output logic                    ALUsrc,     //Inverted flag for R-type Op
    output logic    [1:0]           ALUOp,      //Control signal for ALUdec
    output logic    [1:0]           ImmSrc,     //Controls sign extension block
    output logic                    Branch      //Flag for B-type Op
);

//ALUOp logic: ALUOp determines how the ALUCtrl is decoded.
always_comb
    case(Op)
        //Load and Store employ the ALU add configuration
        LOAD: ALUOp = 2'b00;
        STORE: ALUOp = 2'b00;

        //Branch (beq) employs the ALU subtract configuration
        BRANCH: ALUOp = 2'b01;

        //Arithmetic & Logic (A&L) map funct3 to ALUCtrl, using funct7[5] to differentiate add from sub
        REG: ALUOp = 2'b10;
        I_AL: ALUOp = 2'b10; 

        default: ALUOp = 2'b00;
    endcase
    
/*RegWrite LOGIC:   only certain types of instructions write to regFiles, e.g. U-type do not.
                    The true cases are written but the false are given value 0 implicitly by default case*/
always_comb begin
    case (Op)
        //I-type
        LOAD: RegWrite = 1'b1; 
        I_AL: RegWrite = 1'b1;
        JALR: RegWrite = 1'b1;

        //R-type
        REG: RegWrite = 1'b1;

        //U-type
        AUIPC: RegWrite = 1'b1;
        LUI: RegWrite = 1'b1;

        //J-type
        JAL: RegWrite = 1'b1;

        default: RegWrite = 1'b0;
    endcase
end

//ALUsrc LOGIC: all instructions use a form of the immediate (1) apart from R type (0) and Branch
always_comb begin
    ALUsrc = ~(Op == REG | Op == BRANCH);
end

/*ImmSrc LOGIC: The immediate operand is represented by different sections of the instruction word
                depending on the instruction type (I, U, S, B). R-type is don't care*/
always_comb begin
    case (Op)
        //I-type
        LOAD: ImmSrc = 2'b00;
        I_AL: ImmSrc = 2'b00;
        JALR: ImmSrc = 2'b00;

        //S-type
        STORE: ImmSrc = 2'b01;

        //B-type
        BRANCH: ImmSrc = 2'b10;

        //U-type
        AUIPC: ImmSrc = 2'b11;
        LUI:   ImmSrc = 2'b11;

        //R-type XX set to 00

        default: ImmSrc = 2'b00;
    endcase
end

//BRANCH Logic: identity whether instruction is B-type
always_comb
    Branch = (Op == BRANCH);

endmodule

R3/ControlUnit/ALUdec.sv
module ALUdec #(
    input logic     [1:0]       ALUop,
    input logic     [2:0]       funct3,
    input logic                 funct7_5,
    output logic    [2:0]       ALUctrl
);

/*ALUCtrl LOGIC:    this 3-bit control input has been decoded by mapping each bit from funct3 to ALUctrl with
                    a boolean expression.*/
always_comb begin
    case (ALUOp)
        //LOAD & STORE
        2'b00: ALUctrl = 3'b000

        //BRANCH
        2'b01: ALUctrl = 3'b001

        //ARITHMETIC & LOGIC (R or I)
        2'b10:  begin
                ALUctrl[2] = ~(funct3[2]) & funct3[1];
                ALUctrl[1] = funct3[2] & funct3[1];
                ALUctrl[0] = ~(funct3[2])&funct3[1] | funct3[1] & funct3[0] | ~(funct3) & funct7_5;
                end

        default: ALUctrl = 3'b0;
    endcase
end

endmodule

lab4_final/R3/cu.sv
module cu (
    input logic                     EQ,         //high for OpA == OpB
    input logic     [6:0]           Op,         //Ins[6:0]
    input logic     [2:0]           funct3,     //Ins[14:12]
    input logic                     funct7_5,   //Ins[30]
    output logic                    RegWrite,   //Write enable for the register file
    output logic    [2:0]           ALUctrl,    //Configures ALU for required operation
    output logic                    ALUsrc,     //Selects register or immediate operand 
    output logic    [1:0]           ImmSrc,     //Controls sign extension block
    output logic                    PCsrc       //Selects PC addressing between PC:=PC+4 and PC:=Imm32
);

logic   [1:0]         ALUOp;
logic                 Branch;
logic                 NEG;

assign NEG = funct3[0];

ALUdec ALUdec (
    .ALUOp(ALUOp),
    .funct3(funct3),
    .funct7_5(funct7_5),
    .ALUctrl(ALUctrl)
);

MAINdec MAINdec (
    .Op(Op),
    .RegWrite(RegWrite),
    .ALUsrc(ALUsrc),
    .ALUOp(ALUOp),
    .ImmSrc(ImmSrc),
    .Branch(Branch)  
);

//PCsrc logic
always_comb
    PCsrc = (NEG ^ EQ) & Branch;
endmodule

lab4_final/R3/rom.sv
module rom #(
    parameter   ADDRESS_WIDTH = 32,
                PRACTICAL_WIDTH = 20,
                DATA_WIDTH = 8    
)(
    input logic [ADDRESS_WIDTH-1:0] A,
    output logic [31:0] RD
);

logic [DATA_WIDTH-1:0] rom_array [2**PRACTICAL_WIDTH-1:0];
wire [20:1] practA= A[PRACTICAL_WIDTH-1:0];

initial begin
    $display("Loading rom.");
    $readmemh("program.mem", rom_array);
end

always_comb begin
    // output is asynchronous
    RD = {rom_array[practA], rom_array[practA+1], rom_array[practA+2], rom_array[practA+3]};
end

endmodule

lab4_final/R3/control.sv
module control (
    //input logic                     clk,
    input logic     [31:0]          PC,
    input logic                     EQ,

    output logic                    RegWrite,   //Write enable for the register file
    output logic    [2:0]           ALUctrl,    //Configures ALU for required operation
    output logic                    ALUsrc,     //Selects register or immediate operand 
    output logic                    PCsrc,       //Selects PC addressing between PC:=PC+4 and PC:=Imm32
    

    output logic    [4:0]           rs1,
    output logic    [4:0]           rs2,
    output logic    [4:0]           rd,

    output logic    [31:0]          ImmOp
);

logic [31:0]    ins;
wire [1:0]     ImmSrc;
//logic [31:0] PC1;

rom rom (
    .A(PC), //change to PC1 for individual testing
    .RD(ins)
);

cu cu (
    .EQ(EQ),
    .Op(ins[6:0]),
    .funct3(ins[14:12]),
    .funct7_5(ins[30]),
    .RegWrite(RegWrite),
    .ALUctrl(ALUctrl),
    .ALUsrc(ALUsrc),
    .ImmSrc(ImmSrc),
    .PCsrc(PCsrc)
);

ext32 ext32 (
    .ImmSrc(ImmSrc),
    .msb25(ins[31:7]),
    .ImmExt(ImmOp)
);

assign rs1 = ins[19:15];
assign rs2 = ins[24:20];
assign rd = ins[11:7];

/*always_ff @(posedge clk)
    PC1 <= PC;*/

endmodule

R1/program_counter.sv
// module program_counter (
//     input  logic        clk,
//     input  logic        rst,
//     input  logic        PCsrc,
//     input  logic [31:0] ImmOp,
//     output logic [31:0] PC
// );
//     logic [31:0] branch_PC;
//     logic [31:0] inc_PC;
//     logic [31:0] next_PC;

//     adder branch_adder(
//         .op1(PC),
//         .op2(ImmOp),
//         .out(branch_PC)
//     );

//     adder inc_adder(
//         .op1(PC),
//         .op2(32'd4),
//         .out(inc_PC)
//     );

//     mux branch_sel(
//         .in1(branch_PC),
//         .in2(inc_PC),
//         .sel(PCsrc),
//         .out(next_PC)
//     );

//     register PCReg(
//         .clk(clk),
//         .rst(rst),
//         .in(next_PC),
//         .out(PC)
//     );

// endmodule

module program_counter (
    input  logic        clk,
    input  logic        rst,
    input  logic        PCsrc,
    input  logic [31:0] ImmOp,
    output logic [31:0] PC
);
    logic [31:0] branch_PC;
    logic [31:0] inc_PC;
    logic [31:0] next_PC;

    assign branch_PC = PC + ImmOp;
    assign inc_PC = PC + 32'd4;
    assign next_PC = PCsrc ? branch_PC : inc_PC;

    always_ff @(posedge clk) begin
        if (rst) PC <= 32'd0;
        else PC <= next_PC;
    end

endmodule

lab4_final/top.sv
module top(
    input logic clk,
    input logic rst,
    output logic [31:0] a0
);

    logic PCsrc;
    logic [31:0] ImmOp;
    logic [31:0] pc;
    logic [4:0] ad1;
    logic [4:0] ad2;
    logic [4:0] ad3;
    logic we3;
    logic aluSrc;
    logic [2:0] aluCTR;
    logic eq;

program_counter pcounter(
    .clk (clk),
    .rst (rst),
    .PCsrc (PCsrc),
    .ImmOp (ImmOp),
    .PC (pc)
);

control ctr(
    .PC (pc),
    .EQ (eq),
    .rs1 (ad1),
    .rs2 (ad2),
    .rd (ad3),
    .RegWrite (we3),
    .ALUctrl (aluCTR),
    .ALUsrc (aluSrc),
    //.ImmSrc (immSrc),
    .PCsrc (PCsrc),
    .ImmOp (ImmOp)
);

red alu(
    .clk (clk),
    .a0 (a0),
    .ad1 (ad1),
    .ad2 (ad2),
    .ad3 (ad3),
    .we3 (we3),
    .aluSrc (aluSrc),
    .aluCTR (aluCTR),
    .eq (eq),
    .immOp (ImmOp)
);

endmodule

lab4_final/top.vcd
$version Generated by VerilatedVcd $end
$date Fri Nov 25 12:23:07 2022 $end
$timescale 1ps $end

 $scope module TOP $end
  $var wire 32 ` a0 [31:0] $end
  $var wire  1 ^ clk $end
  $var wire  1 _ rst $end
  $scope module top $end
   $var wire 32 $ ImmOp [31:0] $end
   $var wire  1 # PCsrc $end
   $var wire 32 ` a0 [31:0] $end
   $var wire  5 & ad1 [4:0] $end
   $var wire  5 ' ad2 [4:0] $end
   $var wire  5 ( ad3 [4:0] $end
   $var wire  3 + aluCTR [2:0] $end
   $var wire  1 * aluSrc $end
   $var wire  1 ^ clk $end
   $var wire  1 , eq $end
   $var wire 32 % pc [31:0] $end
   $var wire  1 _ rst $end
   $var wire  1 ) we3 $end
   $scope module alu $end
    $var wire 32 a ADDRESS_WIDTH [31:0] $end
    $var wire 32 b DATA_WIDTH [31:0] $end
    $var wire 32 ` a0 [31:0] $end
    $var wire  5 & ad1 [4:0] $end
    $var wire  5 ' ad2 [4:0] $end
    $var wire  5 ( ad3 [4:0] $end
    $var wire  3 + aluCTR [2:0] $end
    $var wire 32 . aluOp1 [31:0] $end
    $var wire 32 0 aluOp2 [31:0] $end
    $var wire 32 - aluOut [31:0] $end
    $var wire  1 * aluSrc $end
    $var wire  1 ^ clk $end
    $var wire  1 , eq $end
    $var wire 32 $ immOp [31:0] $end
    $var wire 32 / regOp2 [31:0] $end
    $var wire  1 ) we3 $end
    $scope module myAlu $end
     $var wire  3 + aluCTR [2:0] $end
     $var wire 32 . aluOp1 [31:0] $end
     $var wire 32 0 aluOp2 [31:0] $end
     $var wire  1 , eq $end
     $var wire 32 - sum [31:0] $end
    $upscope $end
    $scope module myMux $end
     $var wire 32 0 aluOp2 [31:0] $end
     $var wire  1 * aluSrc $end
     $var wire 32 $ immOp [31:0] $end
     $var wire 32 / regOp2 [31:0] $end
    $upscope $end
    $scope module myRegFile $end
     $var wire 32 a ADDRESS_WIDTH [31:0] $end
     $var wire 32 b DATA_WIDTH [31:0] $end
     $var wire 32 ` a0 [31:0] $end
     $var wire  5 & ad1 [4:0] $end
     $var wire  5 ' ad2 [4:0] $end
     $var wire  5 ( ad3 [4:0] $end
     $var wire  1 ^ clk $end
     $var wire 32 . rd1 [31:0] $end
     $var wire 32 / rd2 [31:0] $end
     $var wire 32 1 rom_array[0] [31:0] $end
     $var wire 32 ; rom_array[10] [31:0] $end
     $var wire 32 < rom_array[11] [31:0] $end
     $var wire 32 = rom_array[12] [31:0] $end
     $var wire 32 > rom_array[13] [31:0] $end
     $var wire 32 ? rom_array[14] [31:0] $end
     $var wire 32 @ rom_array[15] [31:0] $end
     $var wire 32 A rom_array[16] [31:0] $end
     $var wire 32 B rom_array[17] [31:0] $end
     $var wire 32 C rom_array[18] [31:0] $end
     $var wire 32 D rom_array[19] [31:0] $end
     $var wire 32 2 rom_array[1] [31:0] $end
     $var wire 32 E rom_array[20] [31:0] $end
     $var wire 32 F rom_array[21] [31:0] $end
     $var wire 32 G rom_array[22] [31:0] $end
     $var wire 32 H rom_array[23] [31:0] $end
     $var wire 32 I rom_array[24] [31:0] $end
     $var wire 32 J rom_array[25] [31:0] $end
     $var wire 32 K rom_array[26] [31:0] $end
     $var wire 32 L rom_array[27] [31:0] $end
     $var wire 32 M rom_array[28] [31:0] $end
     $var wire 32 N rom_array[29] [31:0] $end
     $var wire 32 3 rom_array[2] [31:0] $end
     $var wire 32 O rom_array[30] [31:0] $end
     $var wire 32 P rom_array[31] [31:0] $end
     $var wire 32 4 rom_array[3] [31:0] $end
     $var wire 32 5 rom_array[4] [31:0] $end
     $var wire 32 6 rom_array[5] [31:0] $end
     $var wire 32 7 rom_array[6] [31:0] $end
     $var wire 32 8 rom_array[7] [31:0] $end
     $var wire 32 9 rom_array[8] [31:0] $end
     $var wire 32 : rom_array[9] [31:0] $end
     $var wire 32 - wd3 [31:0] $end
     $var wire  1 ) we3 $end
    $upscope $end
   $upscope $end
   $scope module ctr $end
    $var wire  3 + ALUctrl [2:0] $end
    $var wire  1 * ALUsrc $end
    $var wire  1 , EQ $end
    $var wire 32 $ ImmOp [31:0] $end
    $var wire  2 R ImmSrc [1:0] $end
    $var wire 32 % PC [31:0] $end
    $var wire  1 # PCsrc $end
    $var wire  1 ) RegWrite $end
    $var wire 32 Q ins [31:0] $end
    $var wire  5 ( rd [4:0] $end
    $var wire  5 & rs1 [4:0] $end
    $var wire  5 ' rs2 [4:0] $end
    $scope module cu $end
     $var wire  2 V ALUOp [1:0] $end
     $var wire  3 + ALUctrl [2:0] $end
     $var wire  1 * ALUsrc $end
     $var wire  1 W Branch $end
     $var wire  1 , EQ $end
     $var wire  2 R ImmSrc [1:0] $end
     $var wire  1 X NEG $end
     $var wire  7 S Op [6:0] $end
     $var wire  1 # PCsrc $end
     $var wire  1 ) RegWrite $end
     $var wire  3 T funct3 [2:0] $end
     $var wire  1 U funct7_5 $end
     $scope module ALUdec $end
      $var wire  2 V ALUOp [1:0] $end
      $var wire  3 + ALUctrl [2:0] $end
      $var wire  3 T funct3 [2:0] $end
      $var wire  1 U funct7_5 $end
     $upscope $end
     $scope module MAINdec $end
      $var wire  2 V ALUOp [1:0] $end
      $var wire  1 * ALUsrc $end
      $var wire  7 i AUIPC [6:0] $end
      $var wire  7 h BRANCH [6:0] $end
      $var wire  1 W Branch $end
      $var wire  7 d I_AL [6:0] $end
      $var wire  2 R ImmSrc [1:0] $end
      $var wire  7 k JAL [6:0] $end
      $var wire  7 e JALR [6:0] $end
      $var wire  7 c LOAD [6:0] $end
      $var wire  7 j LUI [6:0] $end
      $var wire  7 S Op [6:0] $end
      $var wire  7 g REG [6:0] $end
      $var wire  1 ) RegWrite $end
      $var wire  7 f STORE [6:0] $end
     $upscope $end
    $upscope $end
    $scope module ext32 $end
     $var wire 32 $ ImmExt [31:0] $end
     $var wire  2 R ImmSrc [1:0] $end
     $var wire 32 b OUT_WIDTH [31:0] $end
     $var wire 25 Y msb25 [31:7] $end
    $upscope $end
    $scope module rom $end
     $var wire 32 % A [31:0] $end
     $var wire 32 b ADDRESS_WIDTH [31:0] $end
     $var wire 32 m DATA_WIDTH [31:0] $end
     $var wire 32 l PRACTICAL_WIDTH [31:0] $end
     $var wire 32 Q RD [31:0] $end
     $var wire 20 Z practA [20:1] $end
    $upscope $end
   $upscope $end
   $scope module pcounter $end
    $var wire 32 $ ImmOp [31:0] $end
    $var wire 32 % PC [31:0] $end
    $var wire  1 # PCsrc $end
    $var wire 32 [ branch_PC [31:0] $end
    $var wire  1 ^ clk $end
    $var wire 32 \ inc_PC [31:0] $end
    $var wire 32 ] next_PC [31:0] $end
    $var wire  1 _ rst $end
   $upscope $end
  $upscope $end
 $upscope $end
$enddefinitions $end


#0
0#
b00000000000000000000000000000000 $
b00000000000000000000000000000000 %
b00000 &
b00000 '
b00000 (
0)
1*
b000 +
1,
b00000000000000000000000000000000 -
b00000000000000000000000000000000 .
b00000000000000000000000000000000 /
b00000000000000000000000000000000 0
b00000000000000000000000000000000 1
b00000000000000000000000000000000 2
b00000000000000000000000000000000 3
b00000000000000000000000000000000 4
b00000000000000000000000000000000 5
b00000000000000000000000000000000 6
b00000000000000000000000000000000 7
b00000000000000000000000000000000 8
b00000000000000000000000000000000 9
b00000000000000000000000000000000 :
b00000000000000000000000000000000 ;
b00000000000000000000000000000000 <
b00000000000000000000000000000000 =
b00000000000000000000000000000000 >
b00000000000000000000000000000000 ?
b00000000000000000000000000000000 @
b00000000000000000000000000000000 A
b00000000000000000000000000000000 B
b00000000000000000000000000000000 C
b00000000000000000000000000000000 D
b00000000000000000000000000000000 E
b00000000000000000000000000000000 F
b00000000000000000000000000000000 G
b00000000000000000000000000000000 H
b00000000000000000000000000000000 I
b00000000000000000000000000000000 J
b00000000000000000000000000000000 K
b00000000000000000000000000000000 L
b00000000000000000000000000000000 M
b00000000000000000000000000000000 N
b00000000000000000000000000000000 O
b00000000000000000000000000000000 P
b00000000000000000000000000000000 Q
b00 R
b0000000 S
b000 T
0U
b00 V
0W
0X
b0000000000000000000000000 Y
b00000000000000000000 Z
b00000000000000000000000000000000 [
b00000000000000000000000000000100 \
b00000000000000000000000000000100 ]
1^
0_
b00000000000000000000000000000000 `
b00000000000000000000000000000101 a
b00000000000000000000000000100000 b
b0000011 c
b0010011 d
b1100111 e
b0100011 f
b0110011 g
b1100011 h
b0010111 i
b0110111 j
b1101111 k
b00000000000000000000000000010100 l
b00000000000000000000000000001000 m
#1
b00000000000000000000000011111111 $
b11111 '
b00110 (
1)
0,
b00000000000000000000000011111111 -
b00000000000000000000000011111111 0
b00001111111100000000001100010011 Q
b0010011 S
b10 V
b0000111111110000000000110 Y
b00000000000000000000000011111111 [
0^
#2
b00000000000000000000000000000000 $
b00000000000000000000000000000100 %
b00000 '
b01010 (
1,
b00000000000000000000000000000000 -
b00000000000000000000000000000000 0
b00000000000000000000000011111111 7
b00000000000000000000010100010011 Q
b0000000000000000000001010 Y
b00000000000000000100 Z
b00000000000000000000000000000100 [
b00000000000000000000000000001000 \
b00000000000000000000000000001000 ]
1^
#3
0^
#4
b00000000000000000000000000001000 %
b01011 (
b00000000000000000000010110010011 Q
b0000000000000000000001011 Y
b00000000000000001000 Z
b00000000000000000000000000001000 [
b00000000000000000000000000001100 \
b00000000000000000000000000001100 ]
1^
#5
0^
#6
b00000000000000000000000000001100 %
b01011 &
b01010 (
b00000000000001011000010100010011 Q
b0000000000000101100001010 Y
b00000000000000001100 Z
b00000000000000000000000000001100 [
b00000000000000000000000000010000 \
b00000000000000000000000000010000 ]
1^
#7
0^
#8
b00000000000000000000000000000001 $
b00000000000000000000000000010000 %
b00001 '
b01011 (
0,
b00000000000000000000000000000001 -
b00000000000000000000000000000001 0
b00000000000101011000010110010011 Q
b0000000000010101100001011 Y
b00000000000000010000 Z
b00000000000000000000000000010001 [
b00000000000000000000000000010100 \
b00000000000000000000000000010100 ]
1^
#9
0^
#10
1#
b11111111111111111111111111111000 $
b00000000000000000000000000010100 %
b00110 '
b11001 (
0)
0*
b001 +
b00000000000000000000000000000000 -
b00000000000000000000000000000001 .
b00000000000000000000000011111111 /
b00000000000000000000000011111111 0
b00000000000000000000000000000001 <
b11111110011001011001110011100011 Q
b10 R
b1100011 S
b001 T
1U
b01 V
1W
1X
b1111111001100101100111001 Y
b00000000000000010100 Z
b00000000000000000000000000001100 [
b00000000000000000000000000011000 \
b00000000000000000000000000001100 ]
1^
#11
0^
#12
0#
b00000000000000000000000000000000 $
b00000000000000000000000000001100 %
b00000 '
b01010 (
1)
1*
b000 +
b00000000000000000000000000000001 -
b00000000000000000000000000000000 /
b00000000000000000000000000000000 0
b00000000000001011000010100010011 Q
b00 R
b0010011 S
b000 T
0U
b10 V
0W
0X
b0000000000000101100001010 Y
b00000000000000001100 Z
b00000000000000000000000000010000 \
b00000000000000000000000000010000 ]
1^
#13
0^
#14
b00000000000000000000000000000001 $
b00000000000000000000000000010000 %
b00001 '
b01011 (
1,
b00000000000000000000000000000010 -
b00000000000000000000000000000001 0
b00000000000000000000000000000001 ;
b00000000000101011000010110010011 Q
b0000000000010101100001011 Y
b00000000000000010000 Z
b00000000000000000000000000010001 [
b00000000000000000000000000010100 \
b00000000000000000000000000010100 ]
1^
b00000000000000000000000000000001 `
#15
0^
#16
1#
b11111111111111111111111111111000 $
b00000000000000000000000000010100 %
b00110 '
b11001 (
0)
0*
b001 +
0,
b00000000000000000000000000000000 -
b00000000000000000000000000000010 .
b00000000000000000000000011111111 /
b00000000000000000000000011111111 0
b00000000000000000000000000000010 <
b11111110011001011001110011100011 Q
b10 R
b1100011 S
b001 T
1U
b01 V
1W
1X
b1111111001100101100111001 Y
b00000000000000010100 Z
b00000000000000000000000000001100 [
b00000000000000000000000000011000 \
b00000000000000000000000000001100 ]
1^
#17
0^
#18
0#
b00000000000000000000000000000000 $
b00000000000000000000000000001100 %
b00000 '
b01010 (
1)
1*
b000 +
b00000000000000000000000000000010 -
b00000000000000000000000000000000 /
b00000000000000000000000000000000 0
b00000000000001011000010100010011 Q
b00 R
b0010011 S
b000 T
0U
b10 V
0W
0X
b0000000000000101100001010 Y
b00000000000000001100 Z
b00000000000000000000000000010000 \
b00000000000000000000000000010000 ]
1^
#19
0^
#20
b00000000000000000000000000000001 $
b00000000000000000000000000010000 %
b00001 '
b01011 (
b00000000000000000000000000000011 -
b00000000000000000000000000000001 0
b00000000000000000000000000000010 ;
b00000000000101011000010110010011 Q
b0000000000010101100001011 Y
b00000000000000010000 Z
b00000000000000000000000000010001 [
b00000000000000000000000000010100 \
b00000000000000000000000000010100 ]
1^
b00000000000000000000000000000010 `
#21
0^
#22
1#
b11111111111111111111111111111000 $
b00000000000000000000000000010100 %
b00110 '
b11001 (
0)
0*
b001 +
b00000000000000000000000000000000 -
b00000000000000000000000000000011 .
b00000000000000000000000011111111 /
b00000000000000000000000011111111 0
b00000000000000000000000000000011 <
b11111110011001011001110011100011 Q
b10 R
b1100011 S
b001 T
1U
b01 V
1W
1X
b1111111001100101100111001 Y
b00000000000000010100 Z
b00000000000000000000000000001100 [
b00000000000000000000000000011000 \
b00000000000000000000000000001100 ]
1^
#23
0^
#24
0#
b00000000000000000000000000000000 $
b00000000000000000000000000001100 %
b00000 '
b01010 (
1)
1*
b000 +
b00000000000000000000000000000011 -
b00000000000000000000000000000000 /
b00000000000000000000000000000000 0
b00000000000001011000010100010011 Q
b00 R
b0010011 S
b000 T
0U
b10 V
0W
0X
b0000000000000101100001010 Y
b00000000000000001100 Z
b00000000000000000000000000010000 \
b00000000000000000000000000010000 ]
1^
#25
0^
#26
b00000000000000000000000000000001 $
b00000000000000000000000000010000 %
b00001 '
b01011 (
b00000000000000000000000000000100 -
b00000000000000000000000000000001 0
b00000000000000000000000000000011 ;
b00000000000101011000010110010011 Q
b0000000000010101100001011 Y
b00000000000000010000 Z
b00000000000000000000000000010001 [
b00000000000000000000000000010100 \
b00000000000000000000000000010100 ]
1^
b00000000000000000000000000000011 `
#27
0^
#28
1#
b11111111111111111111111111111000 $
b00000000000000000000000000010100 %
b00110 '
b11001 (
0)
0*
b001 +
b00000000000000000000000000000000 -
b00000000000000000000000000000100 .
b00000000000000000000000011111111 /
b00000000000000000000000011111111 0
b00000000000000000000000000000100 <
b11111110011001011001110011100011 Q
b10 R
b1100011 S
b001 T
1U
b01 V
1W
1X
b1111111001100101100111001 Y
b00000000000000010100 Z
b00000000000000000000000000001100 [
b00000000000000000000000000011000 \
b00000000000000000000000000001100 ]
1^
#29
0^
#30
0#
b00000000000000000000000000000000 $
b00000000000000000000000000001100 %
b00000 '
b01010 (
1)
1*
b000 +
b00000000000000000000000000000100 -
b00000000000000000000000000000000 /
b00000000000000000000000000000000 0
b00000000000001011000010100010011 Q
b00 R
b0010011 S
b000 T
0U
b10 V
0W
0X
b0000000000000101100001010 Y
b00000000000000001100 Z
b00000000000000000000000000010000 \
b00000000000000000000000000010000 ]
1^
#31
0^
#32
b00000000000000000000000000000001 $
b00000000000000000000000000010000 %
b00001 '
b01011 (
b00000000000000000000000000000101 -
b00000000000000000000000000000001 0
b00000000000000000000000000000100 ;
b00000000000101011000010110010011 Q
b0000000000010101100001011 Y
b00000000000000010000 Z
b00000000000000000000000000010001 [
b00000000000000000000000000010100 \
b00000000000000000000000000010100 ]
1^
b00000000000000000000000000000100 `
#33
0^
#34
1#
b11111111111111111111111111111000 $
b00000000000000000000000000010100 %
b00110 '
b11001 (
0)
0*
b001 +
b00000000000000000000000000000000 -
b00000000000000000000000000000101 .
b00000000000000000000000011111111 /
b00000000000000000000000011111111 0
b00000000000000000000000000000101 <
b11111110011001011001110011100011 Q
b10 R
b1100011 S
b001 T
1U
b01 V
1W
1X
b1111111001100101100111001 Y
b00000000000000010100 Z
b00000000000000000000000000001100 [
b00000000000000000000000000011000 \
b00000000000000000000000000001100 ]
1^
#35
0^
#36
0#
b00000000000000000000000000000000 $
b00000000000000000000000000001100 %
b00000 '
b01010 (
1)
1*
b000 +
b00000000000000000000000000000101 -
b00000000000000000000000000000000 /
b00000000000000000000000000000000 0
b00000000000001011000010100010011 Q
b00 R
b0010011 S
b000 T
0U
b10 V
0W
0X
b0000000000000101100001010 Y
b00000000000000001100 Z
b00000000000000000000000000010000 \
b00000000000000000000000000010000 ]
1^
#37
0^
#38
b00000000000000000000000000000001 $
b00000000000000000000000000010000 %
b00001 '
b01011 (
b00000000000000000000000000000110 -
b00000000000000000000000000000001 0
b00000000000000000000000000000101 ;
b00000000000101011000010110010011 Q
b0000000000010101100001011 Y
b00000000000000010000 Z
b00000000000000000000000000010001 [
b00000000000000000000000000010100 \
b00000000000000000000000000010100 ]
1^
b00000000000000000000000000000101 `
#39
0^
#40
1#
b11111111111111111111111111111000 $
b00000000000000000000000000010100 %
b00110 '
b11001 (
0)
0*
b001 +
b00000000000000000000000000000000 -
b00000000000000000000000000000110 .
b00000000000000000000000011111111 /
b00000000000000000000000011111111 0
b00000000000000000000000000000110 <
b11111110011001011001110011100011 Q
b10 R
b1100011 S
b001 T
1U
b01 V
1W
1X
b1111111001100101100111001 Y
b00000000000000010100 Z
b00000000000000000000000000001100 [
b00000000000000000000000000011000 \
b00000000000000000000000000001100 ]
1^
#41
0^
#42
0#
b00000000000000000000000000000000 $
b00000000000000000000000000001100 %
b00000 '
b01010 (
1)
1*
b000 +
b00000000000000000000000000000110 -
b00000000000000000000000000000000 /
b00000000000000000000000000000000 0
b00000000000001011000010100010011 Q
b00 R
b0010011 S
b000 T
0U
b10 V
0W
0X
b0000000000000101100001010 Y
b00000000000000001100 Z
b00000000000000000000000000010000 \
b00000000000000000000000000010000 ]
1^
#43
0^
#44
b00000000000000000000000000000001 $
b00000000000000000000000000010000 %
b00001 '
b01011 (
b00000000000000000000000000000111 -
b00000000000000000000000000000001 0
b00000000000000000000000000000110 ;
b00000000000101011000010110010011 Q
b0000000000010101100001011 Y
b00000000000000010000 Z
b00000000000000000000000000010001 [
b00000000000000000000000000010100 \
b00000000000000000000000000010100 ]
1^
b00000000000000000000000000000110 `
#45
0^
